nurtelecom_gras_library/JiraServiceDeskClient.py
nurtelecom_gras_library/OracleDataRetriever.py
nurtelecom_gras_library/OracleGeoDataImporter.py
nurtelecom_gras_library/__init__.py
nurtelecom_gras_library/additional_functions.py
nurtelecom_gras_library/updated_connection.py
nurtelecom_gras_library-2.1.3.dist-info/METADATA
nurtelecom_gras_library-2.1.3.dist-info/WHEEL
nurtelecom_gras_library-2.1.3.dist-info/top_level.txt
nurtelecom_gras_library-2.1.3.dist-info/RECORD
