Metadata-Version: 2.4
Name: nurtelecom_gras_library
Version: 2.1.3
Summary: Official Nurtelecom DSML library
Home-page: https://github.com/beksultantuleev/nurtelecom_gras_library.git
Author: Beksultan Tuleev
Author-email: Beksultan Tuleev <beksultan.tuleev.ds@gmail.com>
License: MIT License
Project-URL: Homepage, https://github.com/beksultantuleev/nurtelecom_gras_library.git
Classifier: Development Status :: 5 - Production/Stable
Classifier: Intended Audience :: Developers
Classifier: Topic :: Software Development :: Build Tools
Classifier: License :: OSI Approved :: MIT License
Classifier: Programming Language :: Python :: 3
Classifier: Programming Language :: Python :: 3.10
Classifier: Programming Language :: Python :: 3.11
Classifier: Programming Language :: Python :: 3.12
Requires-Dist: oracledb
Requires-Dist: pandas
Requires-Dist: python-dotenv
Requires-Dist: geopandas
Requires-Dist: sqlalchemy
Requires-Dist: openpyxl
Requires-Dist: requests
Requires-Dist: transliterate
Requires-Dist: hvac
Dynamic: author
Dynamic: home-page
